storlets/__init__.py
storlets/agent/__init__.py
storlets/agent/common/__init__.py
storlets/agent/common/server.py
storlets/agent/common/utils.py
storlets/agent/daemon/__init__.py
storlets/agent/daemon/files.py
storlets/agent/daemon/server.py
storlets/agent/daemon_factory/__init__.py
storlets/agent/daemon_factory/server.py
storlets/gateway/__init__.py
storlets/gateway/loader.py
storlets/gateway/common/__init__.py
storlets/gateway/common/exceptions.py
storlets/gateway/common/file_manager.py
storlets/gateway/common/logger.py
storlets/gateway/common/stob.py
storlets/gateway/gateways/__init__.py
storlets/gateway/gateways/base.py
storlets/gateway/gateways/stub.py
storlets/gateway/gateways/container/__init__.py
storlets/gateway/gateways/container/gateway.py
storlets/gateway/gateways/container/runtime.py
storlets/gateway/gateways/docker/__init__.py
storlets/gateway/gateways/docker/gateway.py
storlets/gateway/gateways/docker/runtime.py
storlets/gateway/gateways/podman/__init__.py
storlets/gateway/gateways/podman/gateway.py
storlets/gateway/gateways/podman/runtime.py
storlets/sbus/__init__.py
storlets/sbus/command.py
storlets/sbus/datagram.py
storlets/sbus/file_description.py
storlets/sbus/sbus.py
storlets/sbus/client/__init__.py
storlets/sbus/client/cli.py
storlets/sbus/client/client.py
storlets/sbus/client/exceptions.py
storlets/swift_middleware/__init__.py
storlets/swift_middleware/storlet_handler.py
storlets/swift_middleware/handlers/__init__.py
storlets/swift_middleware/handlers/base.py
storlets/swift_middleware/handlers/obj.py
storlets/swift_middleware/handlers/proxy.py
storlets/tools/__init__.py
storlets/tools/cluster_config_parser.py
storlets/tools/deploy_storlet.py
storlets/tools/testtools.py
storlets/tools/utils.py
storlets-16.0.0.data/scripts/storlets-daemon
storlets-16.0.0.data/scripts/storlets-daemon-factory
storlets-16.0.0.dist-info/AUTHORS
storlets-16.0.0.dist-info/LICENSE
storlets-16.0.0.dist-info/METADATA
storlets-16.0.0.dist-info/WHEEL
storlets-16.0.0.dist-info/entry_points.txt
storlets-16.0.0.dist-info/pbr.json
storlets-16.0.0.dist-info/top_level.txt
storlets-16.0.0.dist-info/RECORD
