Metadata-Version: 2.1
Name: storlets
Version: 16.0.0
Summary: Middleware and Compute Engine for an OpenStack Swift compute framework that runs compute within a Swift cluster
Home-page: https://docs.openstack.org/storlets/latest/
Author: OpenStack
Author-email: openstack-discuss@lists.openstack.org
Classifier: Environment :: OpenStack
Classifier: Intended Audience :: Information Technology
Classifier: Intended Audience :: System Administrators
Classifier: License :: OSI Approved :: Apache Software License
Classifier: Operating System :: POSIX :: Linux
Classifier: Programming Language :: Python
Classifier: Programming Language :: Python :: 3
Classifier: Programming Language :: Python :: 3.6
Classifier: Programming Language :: Python :: 3.7
Classifier: Programming Language :: Python :: 3.8
Classifier: Programming Language :: Python :: 3.9
Classifier: Programming Language :: Python :: 3.10
Classifier: Programming Language :: Python :: 3.11
Classifier: Programming Language :: Python :: 3 :: Only
Requires-Python: >=3.6
License-File: LICENSE
License-File: AUTHORS
Requires-Dist: pbr >=2.0
Requires-Dist: setuptools >=17.1
Requires-Dist: eventlet >=0.17.4
Requires-Dist: greenlet >=0.3.1
Requires-Dist: stevedore >=1.16.0
Provides-Extra: docker
Requires-Dist: docker >=1.5.0 ; extra == 'docker'
Provides-Extra: podman
Requires-Dist: podman >=5.0.0 ; extra == 'podman'
Provides-Extra: test
Requires-Dist: hacking <3.1.0,>=3.0.1 ; extra == 'test'
Requires-Dist: bashate ; extra == 'test'
Requires-Dist: coverage >=3.6 ; extra == 'test'
Requires-Dist: pexpect ; extra == 'test'
Requires-Dist: oslotest >=1.2.0 ; extra == 'test'
Requires-Dist: stestr >=2.0.0 ; extra == 'test'
Requires-Dist: testscenarios >=0.4 ; extra == 'test'
Requires-Dist: testtools >=0.9.36 ; extra == 'test'
Requires-Dist: python-swiftclient >=3.1.0 ; extra == 'test'
Requires-Dist: python-keystoneclient ; extra == 'test'
Requires-Dist: docker >=1.5.0 ; extra == 'test'
Requires-Dist: podman >=5.0.0 ; extra == 'test'
